cloud_ips/__init__.py
cloud_ips/const.py
cloud_ips/generate.py
cloud_ips/network.py
cloud_ips/tests.py
cloud_ips-0.1.1.dist-info/WHEEL
cloud_ips-0.1.1.dist-info/METADATA
cloud_ips-0.1.1.dist-info/RECORD
