Metadata-Version: 2.1
Name: cloud-ips
Version: 0.1.1
Summary: Fast - microsecond based cloud providers ip address lookup. GCP / AWS / Digital ocean ip ranges support
